leopold/Device Groups/CSV/.gitignore
leopold/Device Groups/HTML/.gitignore
leopold/Device Groups/JSON/.gitignore
leopold/Device Groups/Markdown/.gitignore
leopold/Device Groups/Mindmap/.gitignore
leopold/Device Groups/YAML/.gitignore
leopold/Devices/CSV/.gitignore
leopold/Devices/HTML/.gitignore
leopold/Devices/JSON/.gitignore
leopold/Devices/Markdown/.gitignore
leopold/Devices/Mindmap/.gitignore
leopold/Devices/YAML/.gitignore
leopold/Devices Config YANG Library/CSV/.gitignore
leopold/Devices Config YANG Library/HTML/.gitignore
leopold/Devices Config YANG Library/JSON/.gitignore
leopold/Devices Config YANG Library/Markdown/.gitignore
leopold/Devices Config YANG Library/Mindmap/.gitignore
leopold/Devices Config YANG Library/YAML/.gitignore
leopold/Devices Config YANG Modules State/CSV/.gitignore
leopold/Devices Config YANG Modules State/HTML/.gitignore
leopold/Devices Config YANG Modules State/JSON/.gitignore
leopold/Devices Config YANG Modules State/Markdown/.gitignore
leopold/Devices Config YANG Modules State/Mindmap/.gitignore
leopold/Devices Config YANG Modules State/YAML/.gitignore
leopold/Devices Live Status YANG Library/CSV/.gitignore
leopold/Devices Live Status YANG Library/HTML/.gitignore
leopold/Devices Live Status YANG Library/JSON/.gitignore
leopold/Devices Live Status YANG Library/Markdown/.gitignore
leopold/Devices Live Status YANG Library/Mindmap/.gitignore
leopold/Devices Live Status YANG Library/YAML/.gitignore
leopold/Devices Live Status YANG Modules State/CSV/.gitignore
leopold/Devices Live Status YANG Modules State/HTML/.gitignore
leopold/Devices Live Status YANG Modules State/JSON/.gitignore
leopold/Devices Live Status YANG Modules State/Markdown/.gitignore
leopold/Devices Live Status YANG Modules State/Mindmap/.gitignore
leopold/Devices Live Status YANG Modules State/YAML/.gitignore
leopold/__init__.py
leopold/datatable_footer.j2
leopold/datatable_header.j2
leopold/leopold.py
leopold/nso_csv.j2
leopold/nso_html.j2
leopold/nso_markdown.j2
leopold-0.1.1.dist-info/METADATA
leopold-0.1.1.dist-info/WHEEL
leopold-0.1.1.dist-info/LICENSE
leopold-0.1.1.dist-info/entry_points.txt
leopold-0.1.1.dist-info/RECORD
